{
    "index": "055",
    "verse": {
        "verse_1": [
            {
                "start": 1,
                "end": 2,
                "rule": "lam_shamsiyyah"
            },
            {
                "start": 7,
                "end": 10,
                "rule": "madd_246"
            }
        ],
        "verse_2": [
            {
                "start": 8,
                "end": 9,
                "rule": "hamzat_wasl"
            },
            {
                "start": 15,
                "end": 18,
                "rule": "madd_246"
            }
        ],
        "verse_3": [
            {
                "start": 7,
                "end": 8,
                "rule": "hamzat_wasl"
            },
            {
                "start": 12,
                "end": 16,
                "rule": "ikhfa"
            },
            {
                "start": 13,
                "end": 16,
                "rule": "madd_246"
            }
        ],
        "verse_4": [
            {
                "start": 10,
                "end": 11,
                "rule": "hamzat_wasl"
            },
            {
                "start": 15,
                "end": 18,
                "rule": "madd_246"
            }
        ],
        "verse_5": [
            {
                "start": 1,
                "end": 2,
                "rule": "lam_shamsiyyah"
            },
            {
                "start": 12,
                "end": 13,
                "rule": "hamzat_wasl"
            },
            {
                "start": 28,
                "end": 31,
                "rule": "madd_246"
            }
        ],
        "verse_6": [
            {
                "start": 2,
                "end": 3,
                "rule": "hamzat_wasl"
            },
            {
                "start": 3,
                "end": 4,
                "rule": "lam_shamsiyyah"
            },
            {
                "start": 4,
                "end": 7,
                "rule": "ghunnah"
            },
            {
                "start": 7,
                "end": 9,
                "rule": "qalqalah"
            },
            {
                "start": 14,
                "end": 15,
                "rule": "hamzat_wasl"
            },
            {
                "start": 15,
                "end": 16,
                "rule": "lam_shamsiyyah"
            },
            {
                "start": 30,
                "end": 33,
                "rule": "madd_246"
            }
        ],
        "verse_7": [
            {
                "start": 2,
                "end": 3,
                "rule": "hamzat_wasl"
            },
            {
                "start": 3,
                "end": 4,
                "rule": "lam_shamsiyyah"
            },
            {
                "start": 7,
                "end": 11,
                "rule": "madd_muttasil"
            },
            {
                "start": 33,
                "end": 34,
                "rule": "hamzat_wasl"
            },
            {
                "start": 39,
                "end": 42,
                "rule": "madd_246"
            }
        ],
        "verse_8": [
            {
                "start": 9,
                "end": 11,
                "rule": "qalqalah"
            },
            {
                "start": 15,
                "end": 17,
                "rule": "silent"
            },
            {
                "start": 22,
                "end": 23,
                "rule": "hamzat_wasl"
            },
            {
                "start": 28,
                "end": 31,
                "rule": "madd_246"
            }
        ],
        "verse_9": [
            {
                "start": 10,
                "end": 12,
                "rule": "silent"
            },
            {
                "start": 13,
                "end": 14,
                "rule": "hamzat_wasl"
            },
            {
                "start": 25,
                "end": 26,
                "rule": "hamzat_wasl"
            },
            {
                "start": 50,
                "end": 52,
                "rule": "silent"
            },
            {
                "start": 53,
                "end": 54,
                "rule": "hamzat_wasl"
            },
            {
                "start": 59,
                "end": 62,
                "rule": "madd_246"
            }
        ],
        "verse_10": [
            {
                "start": 2,
                "end": 3,
                "rule": "hamzat_wasl"
            },
            {
                "start": 28,
                "end": 31,
                "rule": "madd_246"
            }
        ],
        "verse_11": [
            {
                "start": 7,
                "end": 10,
                "rule": "madd_2"
            },
            {
                "start": 14,
                "end": 20,
                "rule": "idghaam_ghunnah"
            },
            {
                "start": 20,
                "end": 21,
                "rule": "hamzat_wasl"
            },
            {
                "start": 21,
                "end": 22,
                "rule": "lam_shamsiyyah"
            },
            {
                "start": 22,
                "end": 25,
                "rule": "ghunnah"
            },
            {
                "start": 36,
                "end": 37,
                "rule": "hamzat_wasl"
            },
            {
                "start": 43,
                "end": 46,
                "rule": "madd_246"
            }
        ],
        "verse_12": [
            {
                "start": 2,
                "end": 3,
                "rule": "hamzat_wasl"
            },
            {
                "start": 15,
                "end": 16,
                "rule": "hamzat_wasl"
            },
            {
                "start": 27,
                "end": 28,
                "rule": "hamzat_wasl"
            },
            {
                "start": 28,
                "end": 29,
                "rule": "lam_shamsiyyah"
            },
            {
                "start": 34,
                "end": 37,
                "rule": "madd_246"
            }
        ],
        "verse_13": [
            {
                "start": 13,
                "end": 17,
                "rule": "madd_muttasil"
            },
            {
                "start": 38,
                "end": 41,
                "rule": "madd_246"
            }
        ],
        "verse_14": [
            {
                "start": 7,
                "end": 8,
                "rule": "hamzat_wasl"
            },
            {
                "start": 12,
                "end": 16,
                "rule": "ikhfa"
            },
            {
                "start": 13,
                "end": 16,
                "rule": "madd_2"
            },
            {
                "start": 21,
                "end": 25,
                "rule": "ikhfa"
            },
            {
                "start": 27,
                "end": 30,
                "rule": "madd_2"
            },
            {
                "start": 30,
                "end": 36,
                "rule": "ikhfa"
            },
            {
                "start": 36,
                "end": 37,
                "rule": "hamzat_wasl"
            },
            {
                "start": 41,
                "end": 45,
                "rule": "madd_246"
            }
        ],
        "verse_15": [
            {
                "start": 9,
                "end": 10,
                "rule": "hamzat_wasl"
            },
            {
                "start": 12,
                "end": 16,
                "rule": "madd_6"
            },
            {
                "start": 16,
                "end": 19,
                "rule": "ghunnah"
            },
            {
                "start": 20,
                "end": 27,
                "rule": "idghaam_ghunnah"
            },
            {
                "start": 30,
                "end": 37,
                "rule": "idghaam_ghunnah"
            },
            {
                "start": 34,
                "end": 42,
                "rule": "idghaam_ghunnah"
            },
            {
                "start": 39,
                "end": 43,
                "rule": "madd_246"
            }
        ],
        "verse_16": [
            {
                "start": 13,
                "end": 17,
                "rule": "madd_muttasil"
            },
            {
                "start": 38,
                "end": 41,
                "rule": "madd_246"
            }
        ],
        "verse_17": [
            {
                "start": 6,
                "end": 7,
                "rule": "hamzat_wasl"
            },
            {
                "start": 30,
                "end": 31,
                "rule": "hamzat_wasl"
            },
            {
                "start": 41,
                "end": 43,
                "rule": "madd_246"
            }
        ],
        "verse_18": [
            {
                "start": 13,
                "end": 17,
                "rule": "madd_muttasil"
            },
            {
                "start": 38,
                "end": 41,
                "rule": "madd_246"
            }
        ],
        "verse_19": [
            {
                "start": 7,
                "end": 8,
                "rule": "hamzat_wasl"
            },
            {
                "start": 29,
                "end": 32,
                "rule": "madd_246"
            }
        ],
        "verse_20": [
            {
                "start": 18,
                "end": 25,
                "rule": "idghaam_no_ghunnah"
            },
            {
                "start": 29,
                "end": 31,
                "rule": "qalqalah"
            },
            {
                "start": 33,
                "end": 36,
                "rule": "madd_246"
            }
        ],
        "verse_21": [
            {
                "start": 13,
                "end": 17,
                "rule": "madd_muttasil"
            },
            {
                "start": 38,
                "end": 41,
                "rule": "madd_246"
            }
        ],
        "verse_22": [
            {
                "start": 19,
                "end": 20,
                "rule": "hamzat_wasl"
            },
            {
                "start": 20,
                "end": 21,
                "rule": "lam_shamsiyyah"
            },
            {
                "start": 33,
                "end": 34,
                "rule": "hamzat_wasl"
            },
            {
                "start": 40,
                "end": 43,
                "rule": "madd_246"
            }
        ],
        "verse_23": [
            {
                "start": 13,
                "end": 17,
                "rule": "madd_muttasil"
            },
            {
                "start": 38,
                "end": 41,
                "rule": "madd_246"
            }
        ],
        "verse_24": [
            {
                "start": 7,
                "end": 8,
                "rule": "hamzat_wasl"
            },
            {
                "start": 18,
                "end": 19,
                "rule": "hamzat_wasl"
            },
            {
                "start": 23,
                "end": 26,
                "rule": "ikhfa"
            },
            {
                "start": 37,
                "end": 38,
                "rule": "hamzat_wasl"
            },
            {
                "start": 49,
                "end": 50,
                "rule": "hamzat_wasl"
            },
            {
                "start": 56,
                "end": 59,
                "rule": "madd_246"
            }
        ],
        "verse_25": [
            {
                "start": 13,
                "end": 17,
                "rule": "madd_muttasil"
            },
            {
                "start": 38,
                "end": 41,
                "rule": "madd_246"
            }
        ],
        "verse_26": [
            {
                "start": 21,
                "end": 24,
                "rule": "madd_246"
            }
        ],
        "verse_27": [
            {
                "start": 4,
                "end": 6,
                "rule": "qalqalah"
            },
            {
                "start": 13,
                "end": 15,
                "rule": "qalqalah"
            },
            {
                "start": 30,
                "end": 31,
                "rule": "hamzat_wasl"
            },
            {
                "start": 35,
                "end": 38,
                "rule": "madd_2"
            },
            {
                "start": 43,
                "end": 44,
                "rule": "hamzat_wasl"
            },
            {
                "start": 50,
                "end": 53,
                "rule": "madd_246"
            }
        ],
        "verse_28": [
            {
                "start": 13,
                "end": 17,
                "rule": "madd_muttasil"
            },
            {
                "start": 38,
                "end": 41,
                "rule": "madd_246"
            }
        ],
        "verse_29": [
            {
                "start": 9,
                "end": 12,
                "rule": "madd_2"
            },
            {
                "start": 15,
                "end": 19,
                "rule": "ikhfa"
            },
            {
                "start": 21,
                "end": 22,
                "rule": "hamzat_wasl"
            },
            {
                "start": 22,
                "end": 23,
                "rule": "lam_shamsiyyah"
            },
            {
                "start": 26,
                "end": 29,
                "rule": "madd_2"
            },
            {
                "start": 29,
                "end": 32,
                "rule": "madd_2"
            },
            {
                "start": 37,
                "end": 38,
                "rule": "hamzat_wasl"
            }
        ],
        "verse_30": [
            {
                "start": 13,
                "end": 17,
                "rule": "madd_muttasil"
            },
            {
                "start": 38,
                "end": 41,
                "rule": "madd_246"
            }
        ],
        "verse_31": [
            {
                "start": 26,
                "end": 27,
                "rule": "hamzat_wasl"
            },
            {
                "start": 27,
                "end": 28,
                "rule": "lam_shamsiyyah"
            },
            {
                "start": 33,
                "end": 36,
                "rule": "madd_246"
            }
        ],
        "verse_32": [
            {
                "start": 13,
                "end": 17,
                "rule": "madd_muttasil"
            },
            {
                "start": 38,
                "end": 41,
                "rule": "madd_246"
            }
        ],
        "verse_33": [
            {
                "start": 0,
                "end": 3,
                "rule": "madd_2"
            },
            {
                "start": 12,
                "end": 13,
                "rule": "hamzat_wasl"
            },
            {
                "start": 17,
                "end": 20,
                "rule": "ghunnah"
            },
            {
                "start": 23,
                "end": 24,
                "rule": "hamzat_wasl"
            },
            {
                "start": 28,
                "end": 31,
                "rule": "ikhfa"
            },
            {
                "start": 37,
                "end": 38,
                "rule": "hamzat_wasl"
            },
            {
                "start": 53,
                "end": 57,
                "rule": "ikhfa"
            },
            {
                "start": 57,
                "end": 60,
                "rule": "ikhfa"
            },
            {
                "start": 63,
                "end": 65,
                "rule": "silent"
            },
            {
                "start": 73,
                "end": 75,
                "rule": "qalqalah"
            },
            {
                "start": 81,
                "end": 82,
                "rule": "hamzat_wasl"
            },
            {
                "start": 82,
                "end": 83,
                "rule": "lam_shamsiyyah"
            },
            {
                "start": 86,
                "end": 89,
                "rule": "madd_2"
            },
            {
                "start": 89,
                "end": 92,
                "rule": "madd_2"
            },
            {
                "start": 97,
                "end": 98,
                "rule": "hamzat_wasl"
            },
            {
                "start": 109,
                "end": 110,
                "rule": "hamzat_wasl"
            },
            {
                "start": 110,
                "end": 113,
                "rule": "ikhfa"
            },
            {
                "start": 116,
                "end": 118,
                "rule": "silent"
            },
            {
                "start": 127,
                "end": 130,
                "rule": "ikhfa"
            },
            {
                "start": 149,
                "end": 152,
                "rule": "madd_246"
            }
        ],
        "verse_34": [
            {
                "start": 13,
                "end": 17,
                "rule": "madd_muttasil"
            },
            {
                "start": 38,
                "end": 41,
                "rule": "madd_246"
            }
        ],
        "verse_35": [
            {
                "start": 26,
                "end": 33,
                "rule": "idghaam_ghunnah"
            },
            {
                "start": 30,
                "end": 38,
                "rule": "idghaam_ghunnah"
            },
            {
                "start": 39,
                "end": 45,
                "rule": "idghaam_ghunnah"
            },
            {
                "start": 50,
                "end": 56,
                "rule": "ikhfa"
            },
            {
                "start": 62,
                "end": 65,
                "rule": "ikhfa"
            },
            {
                "start": 67,
                "end": 70,
                "rule": "madd_246"
            }
        ],
        "verse_36": [
            {
                "start": 13,
                "end": 17,
                "rule": "madd_muttasil"
            },
            {
                "start": 38,
                "end": 41,
                "rule": "madd_246"
            }
        ],
        "verse_37": [
            {
                "start": 8,
                "end": 9,
                "rule": "hamzat_wasl"
            },
            {
                "start": 9,
                "end": 12,
                "rule": "ikhfa"
            },
            {
                "start": 18,
                "end": 19,
                "rule": "hamzat_wasl"
            },
            {
                "start": 19,
                "end": 20,
                "rule": "lam_shamsiyyah"
            },
            {
                "start": 23,
                "end": 27,
                "rule": "madd_muttasil"
            },
            {
                "start": 46,
                "end": 52,
                "rule": "ikhfa"
            },
            {
                "start": 52,
                "end": 53,
                "rule": "hamzat_wasl"
            },
            {
                "start": 53,
                "end": 54,
                "rule": "lam_shamsiyyah"
            },
            {
                "start": 57,
                "end": 60,
                "rule": "madd_246"
            }
        ],
        "verse_38": [
            {
                "start": 13,
                "end": 17,
                "rule": "madd_muttasil"
            },
            {
                "start": 38,
                "end": 41,
                "rule": "madd_246"
            }
        ],
        "verse_39": [
            {
                "start": 10,
                "end": 17,
                "rule": "idghaam_no_ghunnah"
            },
            {
                "start": 31,
                "end": 35,
                "rule": "ikhfa"
            },
            {
                "start": 35,
                "end": 39,
                "rule": "iqlab"
            },
            {
                "start": 39,
                "end": 43,
                "rule": "madd_muttasil"
            },
            {
                "start": 47,
                "end": 53,
                "rule": "idghaam_ghunnah"
            },
            {
                "start": 57,
                "end": 61,
                "rule": "madd_6"
            },
            {
                "start": 61,
                "end": 65,
                "rule": "ghunnah"
            }
        ],
        "verse_40": [
            {
                "start": 13,
                "end": 17,
                "rule": "madd_muttasil"
            },
            {
                "start": 38,
                "end": 41,
                "rule": "madd_246"
            }
        ],
        "verse_41": [
            {
                "start": 9,
                "end": 10,
                "rule": "hamzat_wasl"
            },
            {
                "start": 14,
                "end": 16,
                "rule": "qalqalah"
            },
            {
                "start": 29,
                "end": 32,
                "rule": "madd_2"
            },
            {
                "start": 50,
                "end": 51,
                "rule": "hamzat_wasl"
            },
            {
                "start": 51,
                "end": 52,
                "rule": "lam_shamsiyyah"
            },
            {
                "start": 52,
                "end": 55,
                "rule": "ghunnah"
            },
            {
                "start": 55,
                "end": 58,
                "rule": "madd_2"
            },
            {
                "start": 64,
                "end": 65,
                "rule": "hamzat_wasl"
            },
            {
                "start": 69,
                "end": 71,
                "rule": "qalqalah"
            },
            {
                "start": 71,
                "end": 74,
                "rule": "madd_246"
            }
        ],
        "verse_42": [
            {
                "start": 13,
                "end": 17,
                "rule": "madd_muttasil"
            },
            {
                "start": 38,
                "end": 41,
                "rule": "madd_246"
            }
        ],
        "verse_43": [
            {
                "start": 0,
                "end": 3,
                "rule": "madd_2"
            },
            {
                "start": 5,
                "end": 8,
                "rule": "madd_2"
            },
            {
                "start": 13,
                "end": 16,
                "rule": "ghunnah"
            },
            {
                "start": 19,
                "end": 20,
                "rule": "hamzat_wasl"
            },
            {
                "start": 43,
                "end": 44,
                "rule": "hamzat_wasl"
            },
            {
                "start": 48,
                "end": 50,
                "rule": "qalqalah"
            },
            {
                "start": 52,
                "end": 55,
                "rule": "madd_246"
            }
        ],
        "verse_44": [
            {
                "start": 38,
                "end": 41,
                "rule": "madd_246"
            }
        ],
        "verse_45": [
            {
                "start": 13,
                "end": 17,
                "rule": "madd_muttasil"
            },
            {
                "start": 38,
                "end": 41,
                "rule": "madd_246"
            }
        ],
        "verse_46": [
            {
                "start": 28,
                "end": 31,
                "rule": "madd_2"
            },
            {
                "start": 34,
                "end": 37,
                "rule": "ghunnah"
            },
            {
                "start": 37,
                "end": 40,
                "rule": "madd_246"
            }
        ],
        "verse_47": [
            {
                "start": 13,
                "end": 17,
                "rule": "madd_muttasil"
            },
            {
                "start": 38,
                "end": 41,
                "rule": "madd_246"
            }
        ],
        "verse_48": [
            {
                "start": 5,
                "end": 9,
                "rule": "madd_muttasil"
            },
            {
                "start": 14,
                "end": 17,
                "rule": "madd_246"
            }
        ],
        "verse_49": [
            {
                "start": 13,
                "end": 17,
                "rule": "madd_muttasil"
            },
            {
                "start": 38,
                "end": 41,
                "rule": "madd_246"
            }
        ],
        "verse_50": [
            {
                "start": 21,
                "end": 23,
                "rule": "qalqalah"
            },
            {
                "start": 25,
                "end": 28,
                "rule": "madd_246"
            }
        ],
        "verse_51": [
            {
                "start": 13,
                "end": 17,
                "rule": "madd_muttasil"
            },
            {
                "start": 38,
                "end": 41,
                "rule": "madd_246"
            }
        ],
        "verse_52": [
            {
                "start": 11,
                "end": 15,
                "rule": "ikhfa"
            },
            {
                "start": 19,
                "end": 22,
                "rule": "madd_2"
            },
            {
                "start": 26,
                "end": 32,
                "rule": "ikhfa"
            },
            {
                "start": 34,
                "end": 37,
                "rule": "madd_246"
            }
        ],
        "verse_53": [
            {
                "start": 13,
                "end": 17,
                "rule": "madd_muttasil"
            },
            {
                "start": 38,
                "end": 41,
                "rule": "madd_246"
            }
        ],
        "verse_54": [
            {
                "start": 25,
                "end": 31,
                "rule": "iqlab"
            },
            {
                "start": 31,
                "end": 35,
                "rule": "madd_muttasil"
            },
            {
                "start": 54,
                "end": 56,
                "rule": "qalqalah"
            },
            {
                "start": 58,
                "end": 66,
                "rule": "idghaam_ghunnah"
            },
            {
                "start": 72,
                "end": 73,
                "rule": "hamzat_wasl"
            },
            {
                "start": 77,
                "end": 80,
                "rule": "ghunnah"
            },
            {
                "start": 87,
                "end": 90,
                "rule": "madd_246"
            }
        ],
        "verse_55": [
            {
                "start": 13,
                "end": 17,
                "rule": "madd_muttasil"
            },
            {
                "start": 38,
                "end": 41,
                "rule": "madd_246"
            }
        ],
        "verse_56": [
            {
                "start": 5,
                "end": 8,
                "rule": "ghunnah"
            },
            {
                "start": 9,
                "end": 12,
                "rule": "madd_2"
            },
            {
                "start": 14,
                "end": 17,
                "rule": "madd_2"
            },
            {
                "start": 20,
                "end": 21,
                "rule": "hamzat_wasl"
            },
            {
                "start": 21,
                "end": 22,
                "rule": "lam_shamsiyyah"
            },
            {
                "start": 37,
                "end": 39,
                "rule": "qalqalah"
            },
            {
                "start": 45,
                "end": 48,
                "rule": "ghunnah"
            },
            {
                "start": 51,
                "end": 55,
                "rule": "ikhfa"
            },
            {
                "start": 52,
                "end": 58,
                "rule": "ikhfa"
            },
            {
                "start": 58,
                "end": 60,
                "rule": "qalqalah"
            },
            {
                "start": 73,
                "end": 77,
                "rule": "madd_6"
            },
            {
                "start": 77,
                "end": 81,
                "rule": "ghunnah"
            }
        ],
        "verse_57": [
            {
                "start": 13,
                "end": 17,
                "rule": "madd_muttasil"
            },
            {
                "start": 38,
                "end": 41,
                "rule": "madd_246"
            }
        ],
        "verse_58": [
            {
                "start": 4,
                "end": 7,
                "rule": "ghunnah"
            },
            {
                "start": 9,
                "end": 12,
                "rule": "ghunnah"
            },
            {
                "start": 13,
                "end": 14,
                "rule": "hamzat_wasl"
            },
            {
                "start": 27,
                "end": 28,
                "rule": "hamzat_wasl"
            },
            {
                "start": 34,
                "end": 37,
                "rule": "madd_246"
            }
        ],
        "verse_59": [
            {
                "start": 13,
                "end": 17,
                "rule": "madd_muttasil"
            },
            {
                "start": 38,
                "end": 41,
                "rule": "madd_246"
            }
        ],
        "verse_60": [
            {
                "start": 7,
                "end": 11,
                "rule": "madd_muttasil"
            },
            {
                "start": 14,
                "end": 15,
                "rule": "hamzat_wasl"
            },
            {
                "start": 21,
                "end": 24,
                "rule": "madd_2"
            },
            {
                "start": 34,
                "end": 35,
                "rule": "hamzat_wasl"
            },
            {
                "start": 41,
                "end": 44,
                "rule": "madd_246"
            }
        ],
        "verse_61": [
            {
                "start": 13,
                "end": 17,
                "rule": "madd_muttasil"
            },
            {
                "start": 38,
                "end": 41,
                "rule": "madd_246"
            }
        ],
        "verse_62": [
            {
                "start": 4,
                "end": 8,
                "rule": "ikhfa"
            },
            {
                "start": 19,
                "end": 22,
                "rule": "ghunnah"
            },
            {
                "start": 22,
                "end": 25,
                "rule": "madd_246"
            }
        ],
        "verse_63": [
            {
                "start": 13,
                "end": 17,
                "rule": "madd_muttasil"
            },
            {
                "start": 38,
                "end": 41,
                "rule": "madd_246"
            }
        ],
        "verse_64": [
            {
                "start": 2,
                "end": 4,
                "rule": "qalqalah"
            },
            {
                "start": 4,
                "end": 8,
                "rule": "madd_6"
            },
            {
                "start": 8,
                "end": 11,
                "rule": "ghunnah"
            },
            {
                "start": 11,
                "end": 14,
                "rule": "madd_246"
            }
        ],
        "verse_65": [
            {
                "start": 13,
                "end": 17,
                "rule": "madd_muttasil"
            },
            {
                "start": 38,
                "end": 41,
                "rule": "madd_246"
            }
        ],
        "verse_66": [
            {
                "start": 27,
                "end": 30,
                "rule": "madd_246"
            }
        ],
        "verse_67": [
            {
                "start": 13,
                "end": 17,
                "rule": "madd_muttasil"
            },
            {
                "start": 38,
                "end": 41,
                "rule": "madd_246"
            }
        ],
        "verse_68": [
            {
                "start": 9,
                "end": 12,
                "rule": "madd_2"
            },
            {
                "start": 16,
                "end": 22,
                "rule": "idghaam_ghunnah"
            },
            {
                "start": 26,
                "end": 32,
                "rule": "idghaam_ghunnah"
            },
            {
                "start": 34,
                "end": 37,
                "rule": "ghunnah"
            },
            {
                "start": 34,
                "end": 38,
                "rule": "madd_246"
            }
        ],
        "verse_69": [
            {
                "start": 13,
                "end": 17,
                "rule": "madd_muttasil"
            },
            {
                "start": 38,
                "end": 41,
                "rule": "madd_246"
            }
        ],
        "verse_70": [
            {
                "start": 5,
                "end": 8,
                "rule": "ghunnah"
            },
            {
                "start": 13,
                "end": 16,
                "rule": "madd_2"
            },
            {
                "start": 21,
                "end": 24,
                "rule": "madd_246"
            }
        ],
        "verse_71": [
            {
                "start": 13,
                "end": 17,
                "rule": "madd_muttasil"
            },
            {
                "start": 38,
                "end": 41,
                "rule": "madd_246"
            }
        ],
        "verse_72": [
            {
                "start": 3,
                "end": 10,
                "rule": "idghaam_ghunnah"
            },
            {
                "start": 10,
                "end": 12,
                "rule": "qalqalah"
            },
            {
                "start": 15,
                "end": 18,
                "rule": "madd_2"
            },
            {
                "start": 18,
                "end": 24,
                "rule": "ikhfa"
            },
            {
                "start": 26,
                "end": 27,
                "rule": "hamzat_wasl"
            },
            {
                "start": 31,
                "end": 34,
                "rule": "madd_246"
            }
        ],
        "verse_73": [
            {
                "start": 13,
                "end": 17,
                "rule": "madd_muttasil"
            },
            {
                "start": 38,
                "end": 41,
                "rule": "madd_246"
            }
        ],
        "verse_74": [
            {
                "start": 7,
                "end": 9,
                "rule": "qalqalah"
            },
            {
                "start": 15,
                "end": 18,
                "rule": "ghunnah"
            },
            {
                "start": 21,
                "end": 25,
                "rule": "ikhfa"
            },
            {
                "start": 22,
                "end": 28,
                "rule": "ikhfa"
            },
            {
                "start": 28,
                "end": 30,
                "rule": "qalqalah"
            },
            {
                "start": 43,
                "end": 47,
                "rule": "madd_6"
            },
            {
                "start": 47,
                "end": 51,
                "rule": "ghunnah"
            }
        ],
        "verse_75": [
            {
                "start": 13,
                "end": 17,
                "rule": "madd_muttasil"
            },
            {
                "start": 38,
                "end": 41,
                "rule": "madd_246"
            }
        ],
        "verse_76": [
            {
                "start": 34,
                "end": 40,
                "rule": "idghaam_ghunnah"
            },
            {
                "start": 42,
                "end": 44,
                "rule": "qalqalah"
            },
            {
                "start": 54,
                "end": 57,
                "rule": "madd_246"
            }
        ],
        "verse_77": [
            {
                "start": 13,
                "end": 17,
                "rule": "madd_muttasil"
            },
            {
                "start": 38,
                "end": 41,
                "rule": "madd_246"
            }
        ],
        "verse_78": [
            {
                "start": 2,
                "end": 5,
                "rule": "madd_2"
            },
            {
                "start": 10,
                "end": 11,
                "rule": "hamzat_wasl"
            },
            {
                "start": 28,
                "end": 29,
                "rule": "hamzat_wasl"
            },
            {
                "start": 33,
                "end": 36,
                "rule": "madd_2"
            },
            {
                "start": 41,
                "end": 42,
                "rule": "hamzat_wasl"
            },
            {
                "start": 48,
                "end": 51,
                "rule": "madd_246"
            }
        ]
    }
}