{
    "index": "085",
    "verse": {
        "verse_1": "Was-samā'i żātil-burūj(i).",
        "verse_2": "Wal-yaumil-mau‘ūd(i).",
        "verse_3": "Wa syāhidiw wa masyhūd(in).",
        "verse_4": "Qutila aṣḥābul-ukhdūd(i).",
        "verse_5": "An-nāri żātil-waqūd(i).",
        "verse_6": "Iż hum ‘alaihā qu‘ūd(un).",
        "verse_7": "Wa hum ‘alā mā yaf‘alūna bil-mu'minīna syuhūd(un).",
        "verse_8": "Wa mā naqamū minhum illā ay yu'minū billāhil-‘azīzil-ḥamīd(i).",
        "verse_9": "Allażī lahū mulkus-samāwāti wal-arḍ(i), wallāhu ‘alā kulli syai'in syahīd(un).",
        "verse_10": "Innal-lażīna fatanul-mu'minīna wal-mu'mināti ṡumma lam yatūbū fa lahum ‘ażābu jahannama wa lahum ‘ażābul-ḥarīq(i).",
        "verse_11": "Innal-lażīna āmanū wa ‘amiluṣ-ṣāliḥāti lahum jannātun tajrī min taḥtihal-anhār(u), żālikal-fauzul-kabīr(u).",
        "verse_12": "Inna baṭsya rabbika lasyadīd(un).",
        "verse_13": "Innahū huwa yubdi'u wa yu‘īd(u).",
        "verse_14": "Wa huwal-gafūrul-wadūd(u).",
        "verse_15": "Żul-‘arsyil-majīd(i).",
        "verse_16": "Fa‘‘ālul limā yurīd(u).",
        "verse_17": "Hal atāka ḥadīṡul-junūd(i).",
        "verse_18": "Fir‘auna wa ṡamūd(a).",
        "verse_19": "Balil-lażīna kafarū fī takżīb(in).",
        "verse_20": "Wallāhu miw warā'ihim muḥīṭ(un).",
        "verse_21": "Bal huwa qur'ānum majīd(un).",
        "verse_22": "Fī lauḥim maḥfūẓ(in)."
    }
}